{
"meta":{"test_sets":[],"test_metrics":[],"learn_metrics":[{"best_value":"Min","name":"RMSE"}],"launch_mode":"Train","parameters":"","iteration_count":1000,"learn_sets":["learn"],"name":"experiment"},
"iterations":[
{"learn":[0.4048169807],"iteration":0,"passed_time":0.009344370958,"remaining_time":9.335026587},
{"learn":[0.3981504246],"iteration":1,"passed_time":0.0180027781,"remaining_time":8.98338627},
{"learn":[0.3870370811],"iteration":2,"passed_time":0.02682902425,"remaining_time":8.916179059},
{"learn":[0.3775671682],"iteration":3,"passed_time":0.03546674206,"remaining_time":8.831218774},
{"learn":[0.3692122635],"iteration":4,"passed_time":0.04444727146,"remaining_time":8.845007021},
{"learn":[0.3606032352],"iteration":5,"passed_time":0.05330067924,"remaining_time":8.830145861},
{"learn":[0.3517174814],"iteration":6,"passed_time":0.06215582032,"remaining_time":8.817247082},
{"learn":[0.3451262146],"iteration":7,"passed_time":0.07068062351,"remaining_time":8.764397315},
{"learn":[0.3399725794],"iteration":8,"passed_time":0.07985658437,"remaining_time":8.793097235},
{"learn":[0.3343477621],"iteration":9,"passed_time":0.08890719698,"remaining_time":8.801812501},
{"learn":[0.3283306494],"iteration":10,"passed_time":0.09745197815,"remaining_time":8.761818762},
{"learn":[0.3237662228],"iteration":11,"passed_time":0.1059993542,"remaining_time":8.727280166},
{"learn":[0.3184074288],"iteration":12,"passed_time":0.1147824985,"remaining_time":8.714640461},
{"learn":[0.3127495428],"iteration":13,"passed_time":0.1238012706,"remaining_time":8.719146627},
{"learn":[0.3081469617],"iteration":14,"passed_time":0.1327235993,"remaining_time":8.715516357},
{"learn":[0.3044804196],"iteration":15,"passed_time":0.1415000408,"remaining_time":8.702252511},
{"learn":[0.3025142102],"iteration":16,"passed_time":0.1500867617,"remaining_time":8.67854628},
{"learn":[0.2993355283],"iteration":17,"passed_time":0.1586518014,"remaining_time":8.655337165},
{"learn":[0.2976392071],"iteration":18,"passed_time":0.1672275614,"remaining_time":8.634223041},
{"learn":[0.2944278042],"iteration":19,"passed_time":0.1761928819,"remaining_time":8.633451215},
{"learn":[0.2905410164],"iteration":20,"passed_time":0.1847760961,"remaining_time":8.614085625},
{"learn":[0.2883359974],"iteration":21,"passed_time":0.193368077,"remaining_time":8.59608997},
{"learn":[0.2865741991],"iteration":22,"passed_time":0.2018004646,"remaining_time":8.572132778},
{"learn":[0.2840376703],"iteration":23,"passed_time":0.2105217913,"remaining_time":8.561219513},
{"learn":[0.2812879576],"iteration":24,"passed_time":0.219076872,"remaining_time":8.54399801},
{"learn":[0.2788076518],"iteration":25,"passed_time":0.228025591,"remaining_time":8.542189447},
{"learn":[0.2763690179],"iteration":26,"passed_time":0.2367150171,"remaining_time":8.530507838},
{"learn":[0.2748546258],"iteration":27,"passed_time":0.2456252429,"remaining_time":8.526704859},
{"learn":[0.273847125],"iteration":28,"passed_time":0.2542499459,"remaining_time":8.512989569},
{"learn":[0.2729332563],"iteration":29,"passed_time":0.2628349636,"remaining_time":8.498330489},
{"learn":[0.2716247077],"iteration":30,"passed_time":0.2716069266,"remaining_time":8.489906833},
{"learn":[0.2708081627],"iteration":31,"passed_time":0.2802809534,"remaining_time":8.47849884},
{"learn":[0.2692808151],"iteration":32,"passed_time":0.2896075906,"remaining_time":8.486380004},
{"learn":[0.2687507037],"iteration":33,"passed_time":0.2981956741,"remaining_time":8.472265329},
{"learn":[0.2673402887],"iteration":34,"passed_time":0.3047276395,"remaining_time":8.401776346},
{"learn":[0.265350527],"iteration":35,"passed_time":0.3132558692,"remaining_time":8.388296053},
{"learn":[0.2636392404],"iteration":36,"passed_time":0.3221420593,"remaining_time":8.384400084},
{"learn":[0.2620831833],"iteration":37,"passed_time":0.3308026806,"remaining_time":8.37453102},
{"learn":[0.2617895852],"iteration":38,"passed_time":0.3392921767,"remaining_time":8.360507226},
{"learn":[0.2599742258],"iteration":39,"passed_time":0.3483325198,"remaining_time":8.359980475},
{"learn":[0.2581937515],"iteration":40,"passed_time":0.3573305324,"remaining_time":8.358048308},
{"learn":[0.2574934236],"iteration":41,"passed_time":0.3620314175,"remaining_time":8.257764237},
{"learn":[0.2558007842],"iteration":42,"passed_time":0.3711132695,"remaining_time":8.259427881},
{"learn":[0.2543396182],"iteration":43,"passed_time":0.3797847615,"remaining_time":8.25168709},
{"learn":[0.2539024274],"iteration":44,"passed_time":0.3886146946,"remaining_time":8.247267408},
{"learn":[0.253877429],"iteration":45,"passed_time":0.3913519674,"remaining_time":8.116299498},
{"learn":[0.2533646295],"iteration":46,"passed_time":0.3997844351,"remaining_time":8.106267375},
{"learn":[0.2529820059],"iteration":47,"passed_time":0.4082837599,"remaining_time":8.097627904},
{"learn":[0.2522033212],"iteration":48,"passed_time":0.4171277497,"remaining_time":8.095683469},
{"learn":[0.2518148173],"iteration":49,"passed_time":0.4259247904,"remaining_time":8.092571017},
{"learn":[0.2500851325],"iteration":50,"passed_time":0.4345604743,"remaining_time":8.08623314},
{"learn":[0.2496348812],"iteration":51,"passed_time":0.4433387693,"remaining_time":8.082406795},
{"learn":[0.2486337769],"iteration":52,"passed_time":0.4519421118,"remaining_time":8.075267545},
{"learn":[0.2482798009],"iteration":53,"passed_time":0.460695229,"remaining_time":8.0706979},
{"learn":[0.2478906713],"iteration":54,"passed_time":0.4692547381,"remaining_time":8.062649591},
{"learn":[0.2471882034],"iteration":55,"passed_time":0.4782333238,"remaining_time":8.061647459},
{"learn":[0.2464215527],"iteration":56,"passed_time":0.4872735868,"remaining_time":8.06138583},
{"learn":[0.2452129343],"iteration":57,"passed_time":0.4961237584,"remaining_time":8.057734145},
{"learn":[0.244407882],"iteration":58,"passed_time":0.5045963223,"remaining_time":8.047883717},
{"learn":[0.2435202569],"iteration":59,"passed_time":0.5131799273,"remaining_time":8.03981886},
{"learn":[0.2430228308],"iteration":60,"passed_time":0.5221843821,"remaining_time":8.038215325},
{"learn":[0.2425013721],"iteration":61,"passed_time":0.5308527282,"remaining_time":8.031288049},
{"learn":[0.2422143346],"iteration":62,"passed_time":0.5394661598,"remaining_time":8.023488758},
{"learn":[0.2416221655],"iteration":63,"passed_time":0.5477999199,"remaining_time":8.011573828},
{"learn":[0.2409675565],"iteration":64,"passed_time":0.5566337905,"remaining_time":8.006962987},
{"learn":[0.2400553785],"iteration":65,"passed_time":0.5653703362,"remaining_time":8.000846879},
{"learn":[0.238948042],"iteration":66,"passed_time":0.5742980753,"remaining_time":7.997314988},
{"learn":[0.2387938157],"iteration":67,"passed_time":0.5826951357,"remaining_time":7.986350977},
{"learn":[0.2377746645],"iteration":68,"passed_time":0.5921935193,"remaining_time":7.990321254},
{"learn":[0.2367992982],"iteration":69,"passed_time":0.6008804607,"remaining_time":7.983126121},
{"learn":[0.2363076447],"iteration":70,"passed_time":0.6093601482,"remaining_time":7.97317715},
{"learn":[0.2360229293],"iteration":71,"passed_time":0.6180178439,"remaining_time":7.965563322},
{"learn":[0.2359029989],"iteration":72,"passed_time":0.6269980327,"remaining_time":7.962016114},
{"learn":[0.2357218861],"iteration":73,"passed_time":0.6354823189,"remaining_time":7.952116585},
{"learn":[0.2355025961],"iteration":74,"passed_time":0.644550014,"remaining_time":7.949450172},
{"learn":[0.2349485297],"iteration":75,"passed_time":0.6537390998,"remaining_time":7.94809116},
{"learn":[0.2344811511],"iteration":76,"passed_time":0.6622640933,"remaining_time":7.938568288},
{"learn":[0.2343534061],"iteration":77,"passed_time":0.6708192843,"remaining_time":7.92942795},
{"learn":[0.233345767],"iteration":78,"passed_time":0.6795697965,"remaining_time":7.922579526},
{"learn":[0.2329779368],"iteration":79,"passed_time":0.6887997399,"remaining_time":7.921197009},
{"learn":[0.2324416836],"iteration":80,"passed_time":0.6973230703,"remaining_time":7.911603724},
{"learn":[0.2322177885],"iteration":81,"passed_time":0.7062456095,"remaining_time":7.906505726},
{"learn":[0.2313665272],"iteration":82,"passed_time":0.7151062811,"remaining_time":7.900632045},
{"learn":[0.2309612315],"iteration":83,"passed_time":0.7240950862,"remaining_time":7.896084512},
{"learn":[0.2301278264],"iteration":84,"passed_time":0.7309031464,"remaining_time":7.867957399},
{"learn":[0.2299124353],"iteration":85,"passed_time":0.7396109073,"remaining_time":7.860515922},
{"learn":[0.2294669307],"iteration":86,"passed_time":0.7481789628,"remaining_time":7.85157923},
{"learn":[0.2293040678],"iteration":87,"passed_time":0.7566696511,"remaining_time":7.841849111},
{"learn":[0.2286925056],"iteration":88,"passed_time":0.7656081907,"remaining_time":7.836731031},
{"learn":[0.2286222792],"iteration":89,"passed_time":0.774457661,"remaining_time":7.830627461},
{"learn":[0.2279278744],"iteration":90,"passed_time":0.7836024326,"remaining_time":7.82741331},
{"learn":[0.2278639385],"iteration":91,"passed_time":0.7923705683,"remaining_time":7.820353},
{"learn":[0.2277399931],"iteration":92,"passed_time":0.8011632206,"remaining_time":7.813495065},
{"learn":[0.227550243],"iteration":93,"passed_time":0.8098966503,"remaining_time":7.806025161},
{"learn":[0.227457286],"iteration":94,"passed_time":0.8183131376,"remaining_time":7.795509364},
{"learn":[0.226671094],"iteration":95,"passed_time":0.8272614658,"remaining_time":7.79004547},
{"learn":[0.2263559368],"iteration":96,"passed_time":0.8367750083,"remaining_time":7.789771469},
{"learn":[0.2262592489],"iteration":97,"passed_time":0.8451984789,"remaining_time":7.779275796},
{"learn":[0.2247260507],"iteration":98,"passed_time":0.8544388923,"remaining_time":7.776256989},
{"learn":[0.22350386],"iteration":99,"passed_time":0.863277031,"remaining_time":7.769493279},
{"learn":[0.22296123],"iteration":100,"passed_time":0.8722337251,"remaining_time":7.763743751},
{"learn":[0.2227210894],"iteration":101,"passed_time":0.8810236222,"remaining_time":7.75646287},
{"learn":[0.2217901477],"iteration":102,"passed_time":0.8896264737,"remaining_time":7.747523757},
{"learn":[0.2217003181],"iteration":103,"passed_time":0.8983856925,"remaining_time":7.739938274},
{"learn":[0.2210653307],"iteration":104,"passed_time":0.9074403929,"remaining_time":7.734849063},
{"learn":[0.2197834333],"iteration":105,"passed_time":0.9161332355,"remaining_time":7.726633137},
{"learn":[0.2183355492],"iteration":106,"passed_time":0.9255843593,"remaining_time":7.724736756},
{"learn":[0.2181480029],"iteration":107,"passed_time":0.934285668,"remaining_time":7.716507554},
{"learn":[0.2178306909],"iteration":108,"passed_time":0.9431463396,"remaining_time":7.709572372},
{"learn":[0.2177233873],"iteration":109,"passed_time":0.9518452838,"remaining_time":7.70129366},
{"learn":[0.2174307573],"iteration":110,"passed_time":0.9603746156,"remaining_time":7.691648948},
{"learn":[0.2170515676],"iteration":111,"passed_time":0.9692193869,"remaining_time":7.684525139},
{"learn":[0.2159261689],"iteration":112,"passed_time":0.9781999965,"remaining_time":7.678437141},
{"learn":[0.2154152054],"iteration":113,"passed_time":0.9871149112,"remaining_time":7.671787818},
{"learn":[0.2152844231],"iteration":114,"passed_time":0.9959752922,"remaining_time":7.664679423},
{"learn":[0.2152426123],"iteration":115,"passed_time":1.004591018,"remaining_time":7.65567638},
{"learn":[0.2147711823],"iteration":116,"passed_time":1.013387608,"remaining_time":7.648044939},
{"learn":[0.2146344036],"iteration":117,"passed_time":1.022484308,"remaining_time":7.642636948},
{"learn":[0.2141641516],"iteration":118,"passed_time":1.031031223,"remaining_time":7.633096705},
{"learn":[0.213668118],"iteration":119,"passed_time":1.039960826,"remaining_time":7.626379391},
{"learn":[0.2129352458],"iteration":120,"passed_time":1.049218422,"remaining_time":7.622008207},
{"learn":[0.2120577603],"iteration":121,"passed_time":1.058469626,"remaining_time":7.617510915},
{"learn":[0.2118257957],"iteration":122,"passed_time":1.067372227,"remaining_time":7.610450758},
{"learn":[0.2117278915],"iteration":123,"passed_time":1.076192452,"remaining_time":7.602778935},
{"learn":[0.2106964055],"iteration":124,"passed_time":1.085478151,"remaining_time":7.59834706},
{"learn":[0.2106509279],"iteration":125,"passed_time":1.093984039,"remaining_time":7.588428966},
{"learn":[0.210093391],"iteration":126,"passed_time":1.102870068,"remaining_time":7.581146218},
{"learn":[0.210055019],"iteration":127,"passed_time":1.111459575,"remaining_time":7.571818352},
{"learn":[0.20997851],"iteration":128,"passed_time":1.120350123,"remaining_time":7.564534551},
{"learn":[0.20994933],"iteration":129,"passed_time":1.128972592,"remaining_time":7.55543196},
{"learn":[0.2098891991],"iteration":130,"passed_time":1.137793257,"remaining_time":7.547651455},
{"learn":[0.2098498731],"iteration":131,"passed_time":1.146418351,"remaining_time":7.538569158},
{"learn":[0.2097640933],"iteration":132,"passed_time":1.155248565,"remaining_time":7.53083087},
{"learn":[0.2097225704],"iteration":133,"passed_time":1.16370094,"remaining_time":7.520634436},
{"learn":[0.2096589273],"iteration":134,"passed_time":1.172406307,"remaining_time":7.512084854},
{"learn":[0.2093751],"iteration":135,"passed_time":1.181133605,"remaining_time":7.503672313},
{"learn":[0.2092695397],"iteration":136,"passed_time":1.189960442,"remaining_time":7.495882201},
{"learn":[0.2092423316],"iteration":137,"passed_time":1.198391567,"remaining_time":7.485605297},
{"learn":[0.2092123945],"iteration":138,"passed_time":1.206854914,"remaining_time":7.475554537},
{"learn":[0.2091452814],"iteration":139,"passed_time":1.215482953,"remaining_time":7.46653814},
{"learn":[0.2091079042],"iteration":140,"passed_time":1.224095733,"remaining_time":7.457434291},
{"learn":[0.2090567089],"iteration":141,"passed_time":1.232486382,"remaining_time":7.446995179},
{"learn":[0.2089808794],"iteration":142,"passed_time":1.241376629,"remaining_time":7.439578821},
{"learn":[0.2087980705],"iteration":143,"passed_time":1.249901513,"remaining_time":7.429970104},
{"learn":[0.2083208837],"iteration":144,"passed_time":1.259065411,"remaining_time":7.424144319},
{"learn":[0.2081093064],"iteration":145,"passed_time":1.267833567,"remaining_time":7.415957985},
{"learn":[0.2080440701],"iteration":146,"passed_time":1.276534555,"remaining_time":7.40737398},
{"learn":[0.2071647996],"iteration":147,"passed_time":1.285689015,"remaining_time":7.401398922},
{"learn":[0.2070212374],"iteration":148,"passed_time":1.294605232,"remaining_time":7.394020485},
{"learn":[0.2069954838],"iteration":149,"passed_time":1.303366885,"remaining_time":7.385745682},
{"learn":[0.2062603216],"iteration":150,"passed_time":1.312070258,"remaining_time":7.377136747},
{"learn":[0.2062200178],"iteration":151,"passed_time":1.320787276,"remaining_time":7.368602699},
{"learn":[0.206106947],"iteration":152,"passed_time":1.329248048,"remaining_time":7.358647689},
{"learn":[0.2060114989],"iteration":153,"passed_time":1.337742263,"remaining_time":7.348895807},
{"learn":[0.2059575311],"iteration":154,"passed_time":1.346448451,"remaining_time":7.340315748},
{"learn":[0.205528264],"iteration":155,"passed_time":1.355426085,"remaining_time":7.333202663},
{"learn":[0.2054826632],"iteration":156,"passed_time":1.363874132,"remaining_time":7.32322225},
{"learn":[0.2052591848],"iteration":157,"passed_time":1.372929564,"remaining_time":7.316498055},
{"learn":[0.2052159734],"iteration":158,"passed_time":1.381299563,"remaining_time":7.306119071},
{"learn":[0.2051818167],"iteration":159,"passed_time":1.390143492,"remaining_time":7.298253335},
{"learn":[0.2047831969],"iteration":160,"passed_time":1.398703172,"remaining_time":7.288894169},
{"learn":[0.2047364058],"iteration":161,"passed_time":1.407453133,"remaining_time":7.28052917},
{"learn":[0.2046534455],"iteration":162,"passed_time":1.416231518,"remaining_time":7.272305404},
{"learn":[0.2046425204],"iteration":163,"passed_time":1.424996528,"remaining_time":7.264006692},
{"learn":[0.2041863587],"iteration":164,"passed_time":1.433769834,"remaining_time":7.255744309},
{"learn":[0.2037489455],"iteration":165,"passed_time":1.442672255,"remaining_time":7.248124459},
{"learn":[0.2036062095],"iteration":166,"passed_time":1.451664346,"remaining_time":7.240936528},
{"learn":[0.2035863748],"iteration":167,"passed_time":1.46028977,"remaining_time":7.231911244},
{"learn":[0.2035087284],"iteration":168,"passed_time":1.469025675,"remaining_time":7.223433939},
{"learn":[0.2034826239],"iteration":169,"passed_time":1.477536121,"remaining_time":7.213852824},
{"learn":[0.2034692083],"iteration":170,"passed_time":1.486388046,"remaining_time":7.205939707},
{"learn":[0.2034481846],"iteration":171,"passed_time":1.494930082,"remaining_time":7.196523881},
{"learn":[0.2031564654],"iteration":172,"passed_time":1.503744646,"remaining_time":7.188420936},
{"learn":[0.2028578849],"iteration":173,"passed_time":1.512278376,"remaining_time":7.178976657},
{"learn":[0.2028473758],"iteration":174,"passed_time":1.520760959,"remaining_time":7.169301662},
{"learn":[0.2028359092],"iteration":175,"passed_time":1.529432661,"remaining_time":7.16052564},
{"learn":[0.2028148711],"iteration":176,"passed_time":1.538164828,"remaining_time":7.152031942},
{"learn":[0.2028062656],"iteration":177,"passed_time":1.546549315,"remaining_time":7.141929982},
{"learn":[0.2027790792],"iteration":178,"passed_time":1.555976293,"remaining_time":7.136628695},
{"learn":[0.2024679924],"iteration":179,"passed_time":1.564594113,"remaining_time":7.127595403},
{"learn":[0.2024333892],"iteration":180,"passed_time":1.573028915,"remaining_time":7.117738571},
{"learn":[0.2023979494],"iteration":181,"passed_time":1.581403713,"remaining_time":7.107627677},
{"learn":[0.202321406],"iteration":182,"passed_time":1.59012509,"remaining_time":7.099083052},
{"learn":[0.2018680097],"iteration":183,"passed_time":1.598862698,"remaining_time":7.090608485},
{"learn":[0.2015883019],"iteration":184,"passed_time":1.608316156,"remaining_time":7.085284687},
{"learn":[0.2015738747],"iteration":185,"passed_time":1.616866618,"remaining_time":7.075964661},
{"learn":[0.2015607878],"iteration":186,"passed_time":1.625624504,"remaining_time":7.067554662},
{"learn":[0.201514186],"iteration":187,"passed_time":1.634277902,"remaining_time":7.05868966},
{"learn":[0.2009286158],"iteration":188,"passed_time":1.642972097,"remaining_time":7.05000196},
{"learn":[0.2009202917],"iteration":189,"passed_time":1.651820535,"remaining_time":7.041971755},
{"learn":[0.2009045139],"iteration":190,"passed_time":1.660333766,"remaining_time":7.032513178},
{"learn":[0.2008439791],"iteration":191,"passed_time":1.669040555,"remaining_time":7.023879004},
{"learn":[0.200831932],"iteration":192,"passed_time":1.677438948,"remaining_time":7.013954567},
{"learn":[0.2008068519],"iteration":193,"passed_time":1.686119608,"remaining_time":7.005218577},
{"learn":[0.2007628289],"iteration":194,"passed_time":1.69456471,"remaining_time":6.995510724},
{"learn":[0.2006810155],"iteration":195,"passed_time":1.703223858,"remaining_time":6.986693785},
{"learn":[0.200665573],"iteration":196,"passed_time":1.711829946,"remaining_time":6.977662165},
{"learn":[0.2006489718],"iteration":197,"passed_time":1.720541915,"remaining_time":6.969063715},
{"learn":[0.2005645109],"iteration":198,"passed_time":1.729173431,"remaining_time":6.960140292},
{"learn":[0.200561158],"iteration":199,"passed_time":1.738276393,"remaining_time":6.953105571},
{"learn":[0.2005504076],"iteration":200,"passed_time":1.74691399,"remaining_time":6.94420039},
{"learn":[0.2004567579],"iteration":201,"passed_time":1.755523164,"remaining_time":6.935185569},
{"learn":[0.2002139672],"iteration":202,"passed_time":1.764418542,"remaining_time":6.927298412},
{"learn":[0.2001983761],"iteration":203,"passed_time":1.773272761,"remaining_time":6.919240773},
{"learn":[0.2001151974],"iteration":204,"passed_time":1.782005199,"remaining_time":6.910703088},
{"learn":[0.2001011144],"iteration":205,"passed_time":1.790783704,"remaining_time":6.902341073},
{"learn":[0.2000852719],"iteration":206,"passed_time":1.799397707,"remaining_time":6.893344838},
{"learn":[0.2000740888],"iteration":207,"passed_time":1.808055733,"remaining_time":6.884519907},
{"learn":[0.2000609558],"iteration":208,"passed_time":1.816785506,"remaining_time":6.875968111},
{"learn":[0.1996972826],"iteration":209,"passed_time":1.825462859,"remaining_time":6.867217423},
{"learn":[0.1996763565],"iteration":210,"passed_time":1.834118782,"remaining_time":6.858387292},
{"learn":[0.1996707666],"iteration":211,"passed_time":1.842853243,"remaining_time":6.849850735},
{"learn":[0.1996568866],"iteration":212,"passed_time":1.851863179,"remaining_time":6.842330148},
{"learn":[0.1996454798],"iteration":213,"passed_time":1.860578153,"remaining_time":6.833712283},
{"learn":[0.1993435793],"iteration":214,"passed_time":1.869767139,"remaining_time":6.826824205},
{"learn":[0.1993337805],"iteration":215,"passed_time":1.878306049,"remaining_time":6.817555289},
{"learn":[0.1992648189],"iteration":216,"passed_time":1.88691401,"remaining_time":6.808542258},
{"learn":[0.1992541029],"iteration":217,"passed_time":1.895348963,"remaining_time":6.798912334},
{"learn":[0.1992406114],"iteration":218,"passed_time":1.90425997,"remaining_time":6.790991034},
{"learn":[0.1992220211],"iteration":219,"passed_time":1.912916964,"remaining_time":6.782160146},
{"learn":[0.1991470332],"iteration":220,"passed_time":1.921742549,"remaining_time":6.773925094},
{"learn":[0.199059889],"iteration":221,"passed_time":1.930656201,"remaining_time":6.765993355},
{"learn":[0.1990503026],"iteration":222,"passed_time":1.939637051,"remaining_time":6.758286946},
{"learn":[0.1986655177],"iteration":223,"passed_time":1.948131888,"remaining_time":6.748885468},
{"learn":[0.1986330268],"iteration":224,"passed_time":1.956922867,"remaining_time":6.740512097},
{"learn":[0.1985973189],"iteration":225,"passed_time":1.965604087,"remaining_time":6.731759131},
{"learn":[0.1982704931],"iteration":226,"passed_time":1.974356373,"remaining_time":6.723248794},
{"learn":[0.1982594786],"iteration":227,"passed_time":1.982672329,"remaining_time":6.713258939},
{"learn":[0.1982472746],"iteration":228,"passed_time":1.991127981,"remaining_time":6.703754032},
{"learn":[0.1982432792],"iteration":229,"passed_time":1.99977155,"remaining_time":6.694887362},
{"learn":[0.1982263528],"iteration":230,"passed_time":2.008113726,"remaining_time":6.685019287},
{"learn":[0.1982214914],"iteration":231,"passed_time":2.016478806,"remaining_time":6.675240184},
{"learn":[0.1981873273],"iteration":232,"passed_time":2.024797948,"remaining_time":6.665322},
{"learn":[0.1978180718],"iteration":233,"passed_time":2.033792143,"remaining_time":6.657627272},
{"learn":[0.1978029578],"iteration":234,"passed_time":2.042322016,"remaining_time":6.648409967},
{"learn":[0.1977954924],"iteration":235,"passed_time":2.050847771,"remaining_time":6.639185157},
{"learn":[0.1977800699],"iteration":236,"passed_time":2.059131967,"remaining_time":6.629188569},
{"learn":[0.1971065044],"iteration":237,"passed_time":2.068183141,"remaining_time":6.621661988},
{"learn":[0.1970955392],"iteration":238,"passed_time":2.076649903,"remaining_time":6.612261826},
{"learn":[0.1970796662],"iteration":239,"passed_time":2.085189605,"remaining_time":6.603100416},
{"learn":[0.1968925767],"iteration":240,"passed_time":2.093755717,"remaining_time":6.59402734},
{"learn":[0.1968723914],"iteration":241,"passed_time":2.102743881,"remaining_time":6.586280419},
{"learn":[0.1968361969],"iteration":242,"passed_time":2.111263704,"remaining_time":6.577064297},
{"learn":[0.1968245473],"iteration":243,"passed_time":2.119771856,"remaining_time":6.567817717},
{"learn":[0.1967318726],"iteration":244,"passed_time":2.128390778,"remaining_time":6.55891852},
{"learn":[0.1967204636],"iteration":245,"passed_time":2.136876557,"remaining_time":6.549613512},
{"learn":[0.1966547895],"iteration":246,"passed_time":2.14529604,"remaining_time":6.540113029},
{"learn":[0.1966355405],"iteration":247,"passed_time":2.154099964,"remaining_time":6.531786987},
{"learn":[0.1965542841],"iteration":248,"passed_time":2.162935197,"remaining_time":6.523551538},
{"learn":[0.1965234901],"iteration":249,"passed_time":2.171798654,"remaining_time":6.515395961},
{"learn":[0.1959076734],"iteration":250,"passed_time":2.18070372,"remaining_time":6.507358909},
{"learn":[0.1959045062],"iteration":251,"passed_time":2.189490311,"remaining_time":6.498963303},
{"learn":[0.1958730173],"iteration":252,"passed_time":2.198087652,"remaining_time":6.490005833},
{"learn":[0.1957938611],"iteration":253,"passed_time":2.206535559,"remaining_time":6.48061231},
{"learn":[0.1957838846],"iteration":254,"passed_time":2.215277204,"remaining_time":6.47208438},
{"learn":[0.1957785465],"iteration":255,"passed_time":2.223533727,"remaining_time":6.462144895},
{"learn":[0.1957744123],"iteration":256,"passed_time":2.232237811,"remaining_time":6.453512427},
{"learn":[0.195769552],"iteration":257,"passed_time":2.240543027,"remaining_time":6.443732272},
{"learn":[0.1957635229],"iteration":258,"passed_time":2.24927795,"remaining_time":6.435192898},
{"learn":[0.1957576176],"iteration":259,"passed_time":2.25771163,"remaining_time":6.425794638},
{"learn":[0.1957291334],"iteration":260,"passed_time":2.265968774,"remaining_time":6.415903924},
{"learn":[0.1957228641],"iteration":261,"passed_time":2.274234896,"remaining_time":6.406050966},
{"learn":[0.1956591671],"iteration":262,"passed_time":2.282941013,"remaining_time":6.397443068},
{"learn":[0.1956517173],"iteration":263,"passed_time":2.291338505,"remaining_time":6.387974013},
{"learn":[0.1956422031],"iteration":264,"passed_time":2.299868317,"remaining_time":6.37888005},
{"learn":[0.1956091479],"iteration":265,"passed_time":2.308356451,"remaining_time":6.369675319},
{"learn":[0.1956016519],"iteration":266,"passed_time":2.316917463,"remaining_time":6.360676031},
{"learn":[0.1955973013],"iteration":267,"passed_time":2.325631285,"remaining_time":6.352097391},
{"learn":[0.1955910543],"iteration":268,"passed_time":2.334421753,"remaining_time":6.343726029},
{"learn":[0.1955850197],"iteration":269,"passed_time":2.343041858,"remaining_time":6.334890949},
{"learn":[0.195573854],"iteration":270,"passed_time":2.351423268,"remaining_time":6.325415361},
{"learn":[0.1955295481],"iteration":271,"passed_time":2.359907144,"remaining_time":6.316222062},
{"learn":[0.1955274207],"iteration":272,"passed_time":2.368647266,"remaining_time":6.307716347},
{"learn":[0.1955199305],"iteration":273,"passed_time":2.377218688,"remaining_time":6.298761926},
{"learn":[0.1954994792],"iteration":274,"passed_time":2.386306962,"remaining_time":6.291172901},
{"learn":[0.1953838679],"iteration":275,"passed_time":2.395070149,"remaining_time":6.282720245},
{"learn":[0.195324355],"iteration":276,"passed_time":2.403887418,"remaining_time":6.274406509},
{"learn":[0.194973297],"iteration":277,"passed_time":2.412439783,"remaining_time":6.265401164},
{"learn":[0.1948805601],"iteration":278,"passed_time":2.421195285,"remaining_time":6.256924016},
{"learn":[0.1948495906],"iteration":279,"passed_time":2.429614057,"remaining_time":6.247579003},
{"learn":[0.1948438889],"iteration":280,"passed_time":2.438342747,"remaining_time":6.239033578},
{"learn":[0.194822566],"iteration":281,"passed_time":2.44705645,"remaining_time":6.230448691},
{"learn":[0.194794906],"iteration":282,"passed_time":2.455734444,"remaining_time":6.221772425},
{"learn":[0.1947627393],"iteration":283,"passed_time":2.464571411,"remaining_time":6.213496936},
{"learn":[0.1947528346],"iteration":284,"passed_time":2.473291074,"remaining_time":6.204923221},
{"learn":[0.1945509827],"iteration":285,"passed_time":2.481846896,"remaining_time":6.195939454},
{"learn":[0.1945145879],"iteration":286,"passed_time":2.490300865,"remaining_time":6.186705633},
{"learn":[0.1945007142],"iteration":287,"passed_time":2.499082586,"remaining_time":6.178287505},
{"learn":[0.194441662],"iteration":288,"passed_time":2.507872564,"remaining_time":6.169887172},
{"learn":[0.1944038916],"iteration":289,"passed_time":2.516227975,"remaining_time":6.160420214},
{"learn":[0.1943614859],"iteration":290,"passed_time":2.524640855,"remaining_time":6.151100915},
{"learn":[0.1943537813],"iteration":291,"passed_time":2.533377621,"remaining_time":6.142573137},
{"learn":[0.1943196864],"iteration":292,"passed_time":2.542044344,"remaining_time":6.133874919},
{"learn":[0.1942865132],"iteration":293,"passed_time":2.550708572,"remaining_time":6.125170926},
{"learn":[0.1942845775],"iteration":294,"passed_time":2.559150769,"remaining_time":6.115936583},
{"learn":[0.1942750945],"iteration":295,"passed_time":2.56793252,"remaining_time":6.107515183},
{"learn":[0.1938485143],"iteration":296,"passed_time":2.576970619,"remaining_time":6.099698132},
{"learn":[0.1938380443],"iteration":297,"passed_time":2.585741199,"remaining_time":6.091242691},
{"learn":[0.1938347807],"iteration":298,"passed_time":2.594098935,"remaining_time":6.081817236},
{"learn":[0.193830605],"iteration":299,"passed_time":2.60270348,"remaining_time":6.072974786},
{"learn":[0.19382845],"iteration":300,"passed_time":2.611148431,"remaining_time":6.0637633},
{"learn":[0.1938067204],"iteration":301,"passed_time":2.620074166,"remaining_time":6.055668107},
{"learn":[0.1937756418],"iteration":302,"passed_time":2.628550327,"remaining_time":6.046533261},
{"learn":[0.1937656688],"iteration":303,"passed_time":2.637397754,"remaining_time":6.038252752},
{"learn":[0.1937120561],"iteration":304,"passed_time":2.645872702,"remaining_time":6.029119764},
{"learn":[0.1936959506],"iteration":305,"passed_time":2.65468912,"remaining_time":6.020765519},
{"learn":[0.1936898212],"iteration":306,"passed_time":2.663579077,"remaining_time":6.012574268},
{"learn":[0.1936858572],"iteration":307,"passed_time":2.67197261,"remaining_time":6.003263138},
{"learn":[0.1936596815],"iteration":308,"passed_time":2.680335346,"remaining_time":5.993889074},
{"learn":[0.1936482258],"iteration":309,"passed_time":2.688994995,"remaining_time":5.985182409},
{"learn":[0.1936002116],"iteration":310,"passed_time":2.697701584,"remaining_time":5.976580036},
{"learn":[0.1931052962],"iteration":311,"passed_time":2.70641196,"remaining_time":5.967985347},
{"learn":[0.1930804601],"iteration":312,"passed_time":2.715013419,"remaining_time":5.959150858},
{"learn":[0.1930773183],"iteration":313,"passed_time":2.723437921,"remaining_time":5.949931255},
{"learn":[0.1930752537],"iteration":314,"passed_time":2.732156994,"remaining_time":5.941357272},
{"learn":[0.193060711],"iteration":315,"passed_time":2.740492247,"remaining_time":5.931951572},
{"learn":[0.193052362],"iteration":316,"passed_time":2.749097593,"remaining_time":5.923134561},
{"learn":[0.1929878015],"iteration":317,"passed_time":2.757699432,"remaining_time":5.914311361},
{"learn":[0.1929834368],"iteration":318,"passed_time":2.766670464,"remaining_time":5.906277699},
{"learn":[0.1927588105],"iteration":319,"passed_time":2.77544962,"remaining_time":5.897830443},
{"learn":[0.1927488568],"iteration":320,"passed_time":2.783759295,"remaining_time":5.888388041},
{"learn":[0.1927470674],"iteration":321,"passed_time":2.792074991,"remaining_time":5.878965353},
{"learn":[0.1927293255],"iteration":322,"passed_time":2.801091238,"remaining_time":5.871017858},
{"learn":[0.1927256025],"iteration":323,"passed_time":2.809450035,"remaining_time":5.861692049},
{"learn":[0.1921152038],"iteration":324,"passed_time":2.818321337,"remaining_time":5.853436624},
{"learn":[0.1920835268],"iteration":325,"passed_time":2.826671348,"remaining_time":5.844099659},
{"learn":[0.192061329],"iteration":326,"passed_time":2.835394218,"remaining_time":5.835536112},
{"learn":[0.1920581976],"iteration":327,"passed_time":2.843759007,"remaining_time":5.826237965},
{"learn":[0.1920530538],"iteration":328,"passed_time":2.852308297,"remaining_time":5.817321784},
{"learn":[0.1918528421],"iteration":329,"passed_time":2.860915076,"remaining_time":5.808524548},
{"learn":[0.1912507141],"iteration":330,"passed_time":2.870142334,"remaining_time":5.800982542},
{"learn":[0.1910854738],"iteration":331,"passed_time":2.878590722,"remaining_time":5.79186326},
{"learn":[0.1910836325],"iteration":332,"passed_time":2.887205146,"remaining_time":5.783080577},
{"learn":[0.1910645388],"iteration":333,"passed_time":2.896021493,"remaining_time":5.77470154},
{"learn":[0.1910614002],"iteration":334,"passed_time":2.904349642,"remaining_time":5.765350782},
{"learn":[0.19104303],"iteration":335,"passed_time":2.912853886,"remaining_time":5.756354109},
{"learn":[0.1910410432],"iteration":336,"passed_time":2.921366987,"remaining_time":5.747377782},
{"learn":[0.1910318529],"iteration":337,"passed_time":2.930290418,"remaining_time":5.739207861},
{"learn":[0.1910177988],"iteration":338,"passed_time":2.938676057,"remaining_time":5.729984878},
{"learn":[0.1910145687],"iteration":339,"passed_time":2.94712171,"remaining_time":5.720883319},
{"learn":[0.1910035078],"iteration":340,"passed_time":2.955375127,"remaining_time":5.711414102},
{"learn":[0.1910011939],"iteration":341,"passed_time":2.963916331,"remaining_time":5.70250569},
{"learn":[0.1909956042],"iteration":342,"passed_time":2.972481952,"remaining_time":5.693646188},
{"learn":[0.1909760025],"iteration":343,"passed_time":2.980936983,"remaining_time":5.684577502},
{"learn":[0.1909656655],"iteration":344,"passed_time":2.989248681,"remaining_time":5.675240249},
{"learn":[0.1909632876],"iteration":345,"passed_time":2.997821004,"remaining_time":5.666401552},
{"learn":[0.1909166771],"iteration":346,"passed_time":3.006241429,"remaining_time":5.65727854},
{"learn":[0.1909002632],"iteration":347,"passed_time":3.014554771,"remaining_time":5.647958938},
{"learn":[0.1908849283],"iteration":348,"passed_time":3.023277269,"remaining_time":5.639408316},
{"learn":[0.1908704911],"iteration":349,"passed_time":3.031949172,"remaining_time":5.630762748},
{"learn":[0.1908681665],"iteration":350,"passed_time":3.040260359,"remaining_time":5.621450066},
{"learn":[0.1908525657],"iteration":351,"passed_time":3.048439946,"remaining_time":5.611900811},
{"learn":[0.190836237],"iteration":352,"passed_time":3.056692743,"remaining_time":5.602493497},
{"learn":[0.1908337123],"iteration":353,"passed_time":3.065134969,"remaining_time":5.59343839},
{"learn":[0.1907134095],"iteration":354,"passed_time":3.073880792,"remaining_time":5.584938341},
{"learn":[0.1901679522],"iteration":355,"passed_time":3.082880789,"remaining_time":5.576896707},
{"learn":[0.1901623106],"iteration":356,"passed_time":3.091202386,"remaining_time":5.567627826},
{"learn":[0.1901191958],"iteration":357,"passed_time":3.100477956,"remaining_time":5.560074993},
{"learn":[0.189567686],"iteration":358,"passed_time":3.109399934,"remaining_time":5.551881219},
{"learn":[0.189557263],"iteration":359,"passed_time":3.117834395,"remaining_time":5.542816703},
{"learn":[0.1893519228],"iteration":360,"passed_time":3.126692292,"remaining_time":5.534505192},
{"learn":[0.1893393002],"iteration":361,"passed_time":3.135445399,"remaining_time":5.526005979},
{"learn":[0.1893383299],"iteration":362,"passed_time":3.1437589,"remaining_time":5.516733938},
{"learn":[0.1893367555],"iteration":363,"passed_time":3.15275511,"remaining_time":5.508660027},
{"learn":[0.1893012534],"iteration":364,"passed_time":3.161452831,"remaining_time":5.500061775},
{"learn":[0.1892884992],"iteration":365,"passed_time":3.16983316,"remaining_time":5.490913179},
{"learn":[0.1889749231],"iteration":366,"passed_time":3.178521374,"remaining_time":5.482299808},
{"learn":[0.1887834372],"iteration":367,"passed_time":3.187146147,"remaining_time":5.473577079},
{"learn":[0.1885234166],"iteration":368,"passed_time":3.195914563,"remaining_time":5.465100513},
{"learn":[0.1885143793],"iteration":369,"passed_time":3.204467279,"remaining_time":5.456255098},
{"learn":[0.1885124945],"iteration":370,"passed_time":3.213112562,"remaining_time":5.447568198},
{"learn":[0.1885097364],"iteration":371,"passed_time":3.22175582,"remaining_time":5.438878105},
{"learn":[0.1884976642],"iteration":372,"passed_time":3.230464172,"remaining_time":5.430297683},
{"learn":[0.1884959816],"iteration":373,"passed_time":3.238858097,"remaining_time":5.42119029},
{"learn":[0.1883623811],"iteration":374,"passed_time":3.247711945,"remaining_time":5.412853242},
{"learn":[0.1883608537],"iteration":375,"passed_time":3.256055784,"remaining_time":5.403667046},
{"learn":[0.188354247],"iteration":376,"passed_time":3.264741894,"remaining_time":5.395050929},
{"learn":[0.1880598594],"iteration":377,"passed_time":3.273609248,"remaining_time":5.386732679},
{"learn":[0.1880174701],"iteration":378,"passed_time":3.282626888,"remaining_time":5.378657778},
{"learn":[0.1880151747],"iteration":379,"passed_time":3.291275808,"remaining_time":5.369976318},
{"learn":[0.1879802344],"iteration":380,"passed_time":3.299930197,"remaining_time":5.361303916},
{"learn":[0.1878933626],"iteration":381,"passed_time":3.308516848,"remaining_time":5.352522021},
{"learn":[0.1878409803],"iteration":382,"passed_time":3.317201194,"remaining_time":5.34389853},
{"learn":[0.1877918321],"iteration":383,"passed_time":3.325726278,"remaining_time":5.335019238},
{"learn":[0.1877871159],"iteration":384,"passed_time":3.334562573,"remaining_time":5.326638916},
{"learn":[0.187546018],"iteration":385,"passed_time":3.343085753,"remaining_time":5.317758167},
{"learn":[0.1875241149],"iteration":386,"passed_time":3.351946525,"remaining_time":5.309414005},
{"learn":[0.1875234032],"iteration":387,"passed_time":3.36027214,"remaining_time":5.300223066},
{"learn":[0.1872537103],"iteration":388,"passed_time":3.369061145,"remaining_time":5.291764421},
{"learn":[0.1871955754],"iteration":389,"passed_time":3.377899925,"remaining_time":5.283381934},
{"learn":[0.1871924923],"iteration":390,"passed_time":3.38628353,"remaining_time":5.274288158},
{"learn":[0.1870577199],"iteration":391,"passed_time":3.395137739,"remaining_time":5.265927922},
{"learn":[0.1870452112],"iteration":392,"passed_time":3.40382448,"remaining_time":5.257306513},
{"learn":[0.1867921145],"iteration":393,"passed_time":3.412855195,"remaining_time":5.249213828},
{"learn":[0.1867885237],"iteration":394,"passed_time":3.421648388,"remaining_time":5.240752595},
{"learn":[0.1864222661],"iteration":395,"passed_time":3.430497869,"remaining_time":5.232375537},
{"learn":[0.1861579606],"iteration":396,"passed_time":3.439545806,"remaining_time":5.224297534},
{"learn":[0.1860902167],"iteration":397,"passed_time":3.448309904,"remaining_time":5.215785332},
{"learn":[0.1860879162],"iteration":398,"passed_time":3.456547301,"remaining_time":5.206478516},
{"learn":[0.1860871711],"iteration":399,"passed_time":3.465249421,"remaining_time":5.197874132},
{"learn":[0.1857491109],"iteration":400,"passed_time":3.47429807,"remaining_time":5.189786893},
{"learn":[0.1856993158],"iteration":401,"passed_time":3.483202836,"remaining_time":5.181480835},
{"learn":[0.1856971318],"iteration":402,"passed_time":3.491498603,"remaining_time":5.172269643},
{"learn":[0.1856183328],"iteration":403,"passed_time":3.50014107,"remaining_time":5.16357445},
{"learn":[0.1856163719],"iteration":404,"passed_time":3.508589809,"remaining_time":5.154594904},
{"learn":[0.1855918598],"iteration":405,"passed_time":3.517391609,"remaining_time":5.146134521},
{"learn":[0.1851577709],"iteration":406,"passed_time":3.526471286,"remaining_time":5.138077329},
{"learn":[0.1851150728],"iteration":407,"passed_time":3.535276823,"remaining_time":5.129617351},
{"learn":[0.1851130598],"iteration":408,"passed_time":3.543827636,"remaining_time":5.120787611},
{"learn":[0.1851098765],"iteration":409,"passed_time":3.552362077,"remaining_time":5.111935672},
{"learn":[0.1851069927],"iteration":410,"passed_time":3.561173485,"remaining_time":5.103482197},
{"learn":[0.1850783021],"iteration":411,"passed_time":3.56987271,"remaining_time":5.094866877},
{"learn":[0.1850684691],"iteration":412,"passed_time":3.578594027,"remaining_time":5.086282551},
{"learn":[0.1850644983],"iteration":413,"passed_time":3.587031794,"remaining_time":5.077296211},
{"learn":[0.1850601903],"iteration":414,"passed_time":3.595733734,"remaining_time":5.068684903},
{"learn":[0.1850237365],"iteration":415,"passed_time":3.604422579,"remaining_time":5.060054775},
{"learn":[0.1850165423],"iteration":416,"passed_time":3.613086156,"remaining_time":5.051389039},
{"learn":[0.185013835],"iteration":417,"passed_time":3.621557287,"remaining_time":5.042455362},
{"learn":[0.1850134509],"iteration":418,"passed_time":3.62990794,"remaining_time":5.033356833},
{"learn":[0.1850045232],"iteration":419,"passed_time":3.638619358,"remaining_time":5.024760065},
{"learn":[0.1849798363],"iteration":420,"passed_time":3.647481963,"remaining_time":5.01637068},
{"learn":[0.1849142289],"iteration":421,"passed_time":3.656160729,"remaining_time":5.007727254},
{"learn":[0.1848705933],"iteration":422,"passed_time":3.665168059,"remaining_time":4.999531844},
{"learn":[0.1848677246],"iteration":423,"passed_time":3.673691089,"remaining_time":4.990674687},
{"learn":[0.1847937585],"iteration":424,"passed_time":3.682467701,"remaining_time":4.982162183},
{"learn":[0.1847862739],"iteration":425,"passed_time":3.691169911,"remaining_time":4.97354819},
{"learn":[0.1847837415],"iteration":426,"passed_time":3.699901267,"remaining_time":4.964972894},
{"learn":[0.184773921],"iteration":427,"passed_time":3.708543133,"remaining_time":4.956277271},
{"learn":[0.1847701971],"iteration":428,"passed_time":3.717156574,"remaining_time":4.947544065},
{"learn":[0.1847682085],"iteration":429,"passed_time":3.725510082,"remaining_time":4.938466853},
{"learn":[0.1847491938],"iteration":430,"passed_time":3.734002744,"remaining_time":4.929576708},
{"learn":[0.184747918],"iteration":431,"passed_time":3.74236587,"remaining_time":4.920518088},
{"learn":[0.1847448878],"iteration":432,"passed_time":3.750679752,"remaining_time":4.911398197},
{"learn":[0.1847382082],"iteration":433,"passed_time":3.75889676,"remaining_time":4.902155683},
{"learn":[0.1847328605],"iteration":434,"passed_time":3.767401285,"remaining_time":4.893291324},
{"learn":[0.1847265181],"iteration":435,"passed_time":3.776124836,"remaining_time":4.884711944},
{"learn":[0.1847235252],"iteration":436,"passed_time":3.784685658,"remaining_time":4.875922254},
{"learn":[0.1847124253],"iteration":437,"passed_time":3.793080454,"remaining_time":4.866920582},
{"learn":[0.1847037552],"iteration":438,"passed_time":3.801684187,"remaining_time":4.858188676},
{"learn":[0.184663139],"iteration":439,"passed_time":3.810091046,"remaining_time":4.849206786},
{"learn":[0.184643325],"iteration":440,"passed_time":3.81846909,"remaining_time":4.840190978},
{"learn":[0.1846416542],"iteration":441,"passed_time":3.827144269,"remaining_time":4.831553172},
{"learn":[0.1846401993],"iteration":442,"passed_time":3.835587718,"remaining_time":4.822623835},
{"learn":[0.184638444],"iteration":443,"passed_time":3.843792893,"remaining_time":4.813398308},
{"learn":[0.1846360879],"iteration":444,"passed_time":3.85218291,"remaining_time":4.804407899},
{"learn":[0.1845745932],"iteration":445,"passed_time":3.861085782,"remaining_time":4.796057227},
{"learn":[0.184573072],"iteration":446,"passed_time":3.869470649,"remaining_time":4.787063242},
{"learn":[0.1845707433],"iteration":447,"passed_time":3.877837232,"remaining_time":4.778049446},
{"learn":[0.1845389733],"iteration":448,"passed_time":3.886629934,"remaining_time":4.769561456},
{"learn":[0.1845374988],"iteration":449,"passed_time":3.895149978,"remaining_time":4.760738862},
{"learn":[0.1845362966],"iteration":450,"passed_time":3.903764963,"remaining_time":4.752033181},
{"learn":[0.184531516],"iteration":451,"passed_time":3.91225509,"remaining_time":4.743176525},
{"learn":[0.1844844549],"iteration":452,"passed_time":3.920896325,"remaining_time":4.734503951},
{"learn":[0.1844509787],"iteration":453,"passed_time":3.929129023,"remaining_time":4.72534019},
{"learn":[0.1844498136],"iteration":454,"passed_time":3.937712107,"remaining_time":4.716600216},
{"learn":[0.1844405955],"iteration":455,"passed_time":3.946329606,"remaining_time":4.707901986}
]}